project1
gae
apps
