Metadata-Version: 1.0
Name: gaeframework
Version: 2.0.8
Summary: GAE framework is a Python web framework for use on Google App Engine
Home-page: http://www.gaeframework.com
Author: Anton Danilchenko
Author-email: anton.danilchenko@gaeframework.com
License: UNKNOWN
Download-URL: http://code.google.com/p/gaeframework/downloads/list
Platform: UNKNOWN
Classifier: Development Status :: 4 - Beta
Classifier: Environment :: Web Environment
Classifier: Intended Audience :: Developers
Classifier: License :: OSI Approved :: MIT License
Classifier: Operating System :: OS Independent
Classifier: Programming Language :: Python
Classifier: Programming Language :: Python :: 2.6
Classifier: Programming Language :: Python :: 2.7
Classifier: Topic :: Internet :: WWW/HTTP
Classifier: Topic :: Internet :: WWW/HTTP :: Dynamic Content
Classifier: Topic :: Internet :: WWW/HTTP :: WSGI
Classifier: Topic :: Software Development :: Libraries :: Application Frameworks
Classifier: Topic :: Software Development :: Libraries :: Python Modules
